model_utils.py
winningticket-0.0.1.dist-info/LICENSE
winningticket-0.0.1.dist-info/METADATA
winningticket-0.0.1.dist-info/WHEEL
winningticket-0.0.1.dist-info/top_level.txt
winningticket-0.0.1.dist-info/RECORD
