Metadata-Version: 2.1
Name: winningticket
Version: 0.0.1
Summary: Package for easy neural network pruning
Home-page: UNKNOWN
Author: Zack Ankner
Author-email: ankner@mit.edu
License: UNKNOWN
Platform: UNKNOWN
Classifier: Programming Language :: Python :: 3
Classifier: License :: OSI Approved :: MIT License
Classifier: Operating System :: OS Independent
Requires-Python: >=3.6
Requires-Dist: torch (==1.8.0)
Requires-Dist: numpy (==1.21.2)
